amd_libhipmm/__init__.py
amd_libhipmm-0.0.2.dist-info/METADATA
amd_libhipmm-0.0.2.dist-info/WHEEL
amd_libhipmm-0.0.2.dist-info/top_level.txt
amd_libhipmm-0.0.2.dist-info/RECORD
