Metadata-Version: 2.4
Name: amd-libhipmm
Version: 0.0.2
Summary: hipMM - HIP Memory Manager
Author-email: AMD <support@amd.com>
License: Apache 2.0 AND MIT
Project-URL: Homepage, https://github.com/rocm-ds/hipmm
Requires-Python: >=3.8
